setup.py
cachecontrol_django/__init__.py
cachecontrol_django.egg-info/PKG-INFO
cachecontrol_django.egg-info/SOURCES.txt
cachecontrol_django.egg-info/dependency_links.txt
cachecontrol_django.egg-info/requires.txt
cachecontrol_django.egg-info/top_level.txt