Metadata-Version: 2.1
Name: cachecontrol-django
Version: 1.0.0
Summary: A cache provider for CacheControl using Django's caching mechanism.
Home-page: https://github.com/glassesdirect/cachecontrol-django
Author: MyOptique Group
Author-email: tech@myoptiquegroup.com
License: UNKNOWN
Platform: UNKNOWN
Classifier: Programming Language :: Python :: 2.7
Classifier: Programming Language :: Python :: 3.5
Classifier: Programming Language :: Python :: 3.6
Classifier: Programming Language :: Python :: 3.7
Classifier: License :: OSI Approved :: MIT License
Classifier: Operating System :: OS Independent
